{
  "timestamp": "2025-08-20T12:57:23.002384",
  "symbols": [
    "AAMI",
    "AAPX",
    "ADSE",
    "ADV",
    "AENT",
    "AGI",
    "AIBU",
    "AIN",
    "AIOT",
    "ALAB",
    "ALTL",
    "AMDD",
    "AMKR",
    "AMSC",
    "AMZD",
    "AMZN",
    "AMZU",
    "AMZZ",
    "ANET",
    "ANNA",
    "AOTG",
    "APLD",
    "APPF",
    "ARMG",
    "ARMU",
    "ASTL",
    "ASUR",
    "ATAI",
    "ATEC",
    "ATFV",
    "AU",
    "AUGZ",
    "AUR",
    "AVD",
    "AVGG",
    "AVS",
    "AVTX",
    "AX",
    "BBNX",
    "BDC",
    "BDMD",
    "BE",
    "BELT",
    "BEN",
    "BGLC",
    "BIO",
    "BJRI",
    "BKKT",
    "BLIV",
    "BOUT",
    "BOXL",
    "BTSG",
    "BTU",
    "BWEB",
    "BXC",
    "CAPS",
    "CAR",
    "CBZ",
    "CCO",
    "CECO",
    "CETX",
    "CHMG",
    "CINT",
    "CLIX",
    "CMCO",
    "COCP",
    "COHU",
    "COMP",
    "CPNG",
    "CPOP",
    "CRDF",
    "CREG",
    "CRS",
    "CSCL",
    "CSTM",
    "CTKB",
    "CVI",
    "CVNA",
    "CVNX",
    "CWH",
    "DAPP",
    "DARP",
    "DHCNL",
    "DRN",
    "DSGR",
    "DSMC",
    "DSP",
    "DUOT",
    "EBAY",
    "EMN",
    "ENLV",
    "ENTG",
    "EPRX",
    "EPSM",
    "EQRR",
    "EURL",
    "EVR",
    "EWZ",
    "EXR",
    "FAZ",
    "FBIN",
    "FBL",
    "FCA",
    "FDIF",
    "FDMT",
    "FEAM",
    "FFTY",
    "FGF",
    "FGI",
    "FHI",
    "FIG",
    "FIP",
    "FLGC",
    "FLGV",
    "FLYX",
    "FN",
    "FORM",
    "FOXX",
    "FROG",
    "FSTR",
    "FTAI",
    "FTIF",
    "FUBO",
    "FXP",
    "FXZ",
    "G",
    "GAST",
    "GCI",
    "GDMN",
    "GENC",
    "GENI",
    "GIFT",
    "GLE",
    "GMM",
    "GNRC",
    "GOOS",
    "GQI",
    "GTES",
    "HAIL",
    "HBTA",
    "HKIT",
    "HQI",
    "HTCO",
    "HUDI",
    "HWAY",
    "IART",
    "IDCC",
    "INOD",
    "INTJ",
    "IPWR",
    "IQM",
    "IRT",
    "ITT",
    "JEM",
    "JOUT",
    "KALU",
    "KEY",
    "KMB",
    "KNF",
    "KVYO",
    "LASR",
    "LBTYA",
    "LC",
    "LCF",
    "LFUS",
    "LNC",
    "LOGI",
    "LOUP",
    "LPLA",
    "LRCX",
    "LRHC",
    "LSPD",
    "LVLU",
    "LVRO",
    "LVTX",
    "LXEO",
    "MAGX",
    "MATH",
    "MBX",
    "MERC",
    "METU",
    "MGA",
    "MIR",
    "MMLP",
    "MNRS",
    "MOD",
    "MRVL",
    "MTSR",
    "MTZ",
    "MUSA",
    "MUU",
    "MVLL",
    "MVV",
    "MWYN",
    "MYE",
    "MYGN",
    "MYRG",
    "MZZ",
    "NAMM",
    "NCI",
    "NCLH",
    "NEGG",
    "NET",
    "NNE",
    "NRT",
    "NSP",
    "NTGR",
    "NVD",
    "NVDQ",
    "NVST",
    "NVT",
    "OBIO",
    "OMH",
    "ONCO",
    "ONEW",
    "ONLN",
    "OOQB",
    "ORN",
    "PACK",
    "PAPL",
    "PBI",
    "PBM",
    "PHAR",
    "PI",
    "PIII",
    "PJBF",
    "PRLB",
    "PSCI",
    "PTON",
    "PUMP",
    "PVEX",
    "PWR",
    "QCML",
    "QDWN",
    "QQDN",
    "QTWO",
    "QUP",
    "QVMS",
    "RACE",
    "RAYJ",
    "RAYS",
    "RBLU",
    "RBLX",
    "RBRK",
    "RCON",
    "RDDT",
    "RDTL",
    "REPL",
    "REZI",
    "RILYT",
    "RMBS",
    "RMD",
    "RNIN",
    "ROKU",
    "RRX",
    "RSI",
    "SAA",
    "SARK",
    "SATS",
    "SBB",
    "SDD",
    "SETH",
    "SF",
    "SGD",
    "SLXN",
    "SMCZ",
    "SMHX",
    "SMN",
    "SNBR",
    "SNGX",
    "SOFI",
    "SOFL",
    "SOFX",
    "SPCY",
    "SPRU",
    "SPRX",
    "SPXS",
    "SRTS",
    "STKL",
    "STSS",
    "STX",
    "SUPX",
    "SVXY",
    "SWIM",
    "SYNA",
    "TER",
    "TG",
    "THCH",
    "TKR",
    "TNGX",
    "TNK",
    "TNXP",
    "TROX",
    "TSYY",
    "TTMI",
    "TWI",
    "TWNP",
    "TXSS",
    "TYGO",
    "UFG",
    "UMDD",
    "UPB",
    "UPSX",
    "UTHR",
    "UUU",
    "UVIX",
    "UVXY",
    "VATE",
    "VECO",
    "VERS",
    "VGAS",
    "VIVK",
    "VOC",
    "VRME",
    "VRT",
    "VRTL",
    "VSAT",
    "WCC",
    "WDC",
    "WEBL",
    "WEBS",
    "WES",
    "WGS",
    "WHTX",
    "WILD",
    "WUGI",
    "WXET",
    "XBP",
    "XGN",
    "XOMX",
    "XPRO",
    "XSD",
    "YOSH",
    "ZBRA",
    "ZEUS"
  ],
  "filters": {
    "price_range": {
      "min_price": 1.0,
      "max_price": 500.0
    },
    "price_vs_ma": null,
    "rsi": null,
    "min_avg_volume": null,
    "min_avg_dollar_volume": null,
    "gap": {
      "gap_threshold": 2.0,
      "direction": "both"
    },
    "prev_day_dollar_volume": null,
    "relative_volume": {
      "recent_days": 2,
      "lookback_days": 20,
      "min_ratio": 1.5
    }
  },
  "metadata": {
    "screening_date": "2025-08-01",
    "total_symbols_screened": 9133,
    "total_qualifying_stocks": 335,
    "execution_time_ms": 23445.276021957397
  },
  "count": 335
}